make4db/args.py
make4db/cache.py
make4db/dbclean.py
make4db/dbp.py
make4db/export.py
make4db/gc.py
make4db/itersql.py
make4db/make.py
make4db/obj.py
make4db/refs.py
make4db/runner.py
make4db/util.py
make4db-0.1.3.dist-info/METADATA
make4db-0.1.3.dist-info/WHEEL
make4db-0.1.3.dist-info/entry_points.txt
make4db-0.1.3.dist-info/top_level.txt
make4db-0.1.3.dist-info/RECORD
