Metadata-Version: 2.4
Name: make4db
Version: 0.1.3
Summary: GNU Make like tool for database scripts
Author-email: Paresh Adhia <padhia+github@gmail.com>
Classifier: Programming Language :: Python :: 3
Requires-Python: >=3.11
Requires-Dist: sqlparse
Requires-Dist: yappt
Requires-Dist: make4db-api
Provides-Extra: snowflake
Requires-Dist: make4db-snowflake; extra == "snowflake"
Provides-Extra: postgres
Requires-Dist: make4db-postgres; extra == "postgres"
Provides-Extra: duckdb
Requires-Dist: make4db-duckdb; extra == "duckdb"
